<?xml version="1.0" encoding="UTF-8"?>
<plugin_manifest xmlns="http://www.elgg.org/plugin_manifest/1.8">
	<name>Filtre d'inscription</name>
	<author>Florian DANIEL aka Facyla</author>
	<version>0.4</version>
	<blurb>Filtrage des inscriptions</blurb>
	<description>Filtrage des adresses autorisées à créer un compte. Activez ce plugin si vous souhaitez restreindre l'inscription exclusivement aux adresses email d'un ou de plusieurs noms de domaines, ou interdire la création des comptes à certains domaines.</description>
	<website>http://departements-en-reseaux.fr/</website>
	<copyright>Items International (Facyla), Conseil Général de l'Essonne, Assemblée des Départements de France</copyright>
	<license>GNU Public License version 2</license>
	
	<requires>
		<type>elgg_release</type>
		<version>1.11</version>
	</requires>

	<category>admin</category>
	<category>registration</category>
	<category>filter</category>
	
	<requires>
		<type>plugin</type>
		<name>invitefriends</name>
		<priority>after</priority>
	</requires>
	
	<activate_on_install>false</activate_on_install>
	
</plugin_manifest>


<!--

0.4 : 20150610 - Updated to Elgg 1.11
	- renamed to registration_filter

0.3 : 20150525 - +blacklist mode

0.2.2 : activé à l'installation

0.2.1 : ajustement du filtrage du username : remplacement des '@' par des '_' mais on garde les '.' (le tiret n'étant pas un caractère valide)

0.2 : suppression du username (généré à partir de l'adresse mail d'inscription)

0.1 : première version opérationnelle

//-->

